concog_dreem_lib/Permutation_entropy.py
concog_dreem_lib/__init__.py
concog_dreem_lib/lz78.py
concog_dreem_lib/psd.py
concog_dreem_lib/wsmi.py
concog_dreem_lib/matlab_functions/generate_ogpath.m
concog_dreem_lib-0.1.1.dist-info/LICENSE
concog_dreem_lib-0.1.1.dist-info/METADATA
concog_dreem_lib-0.1.1.dist-info/WHEEL
concog_dreem_lib-0.1.1.dist-info/top_level.txt
concog_dreem_lib-0.1.1.dist-info/RECORD
