Metadata-Version: 2.1
Name: concog_dreem_lib
Version: 0.1.1
Summary: Library for LZ complexity, wSMI calculations, and PSD analysis with EEG data.
Author: Max Hughes
Author-email: hugmax12@gmail.com
License: MIT
Classifier: Programming Language :: Python :: 3
Classifier: Operating System :: OS Independent
Requires-Python: >=3.6
License-File: LICENSE
Requires-Dist: numpy
Requires-Dist: pandas
Requires-Dist: mne
Requires-Dist: scipy
Requires-Dist: fooof
